intellimed/__init__.py
intellimed/Config/__init__.py
intellimed/Config/arguments/__init__.py
intellimed/Config/arguments/arguments.py
intellimed/Config/arguments/get_arguments.py
intellimed/Config/arguments/parse_model_arguments.py
intellimed/Config/load_checkpoint/__init__.py
intellimed/Config/load_checkpoint/load_checkpoint.py
intellimed/Config/logging/__init__.py
intellimed/Config/logging/set_logger.py
intellimed/Data/__init__.py
intellimed/Data/dataset/__init__.py
intellimed/Data/dataset/ner/__init__.py
intellimed/Data/dataset/ner/process.py
intellimed/Data/loader/__init__.py
intellimed/Data/metric/__init__.py
intellimed/Data/metric/ner/__init__.py
intellimed/Data/metric/ner/get_metric.py
intellimed/LLM/__init__.py
intellimed/Model/__init__.py
intellimed/Model/ae/__init__.py
intellimed/Model/ee/__init__.py
intellimed/Model/ner/BiLSTM_CRF.py
intellimed/Model/ner/__init__.py
intellimed/Model/ner/bert/__init__.py
intellimed/Model/ner/peft/__init__.py
intellimed/Model/ner/peft/add_peft_config.py
intellimed/Model/ner/peft/get_peft_model.py
intellimed/Model/re/__init__.py
intellimed/Trainer/Trainer.py
intellimed/Trainer/__init__.py
intellimed/Trainer/infer_bert.py
intellimed-0.0.2.dist-info/LICENSE
intellimed-0.0.2.dist-info/METADATA
intellimed-0.0.2.dist-info/WHEEL
intellimed-0.0.2.dist-info/top_level.txt
intellimed-0.0.2.dist-info/RECORD
